{"base_url":"","routes":{"api_system_status":{"tokens":[["text","\/api\/doc\/system_status"]],"defaults":[],"requirements":[],"hosttokens":[],"methods":["GET"],"schemes":[]},"api_delta_journal":{"tokens":[["text","\/api\/doc\/journal"]],"defaults":[],"requirements":[],"hosttokens":[],"methods":["GET"],"schemes":[]},"delta_journal":{"tokens":[["text","\/delta\/journal"]],"defaults":[],"requirements":[],"hosttokens":[],"methods":[],"schemes":[]},"mail_search":{"tokens":[["text","\/mail\/search"]],"defaults":[],"requirements":[],"hosttokens":[],"methods":[],"schemes":[]},"mail_domain":{"tokens":[["text","\/mail\/domain"]],"defaults":[],"requirements":[],"hosttokens":[],"methods":[],"schemes":[]},"mail_acl":{"tokens":[["text","\/mail\/acl"]],"defaults":[],"requirements":[],"hosttokens":[],"methods":[],"schemes":[]},"core_status":{"tokens":[["text","\/status"]],"defaults":[],"requirements":[],"hosttokens":[],"methods":[],"schemes":[]}},"prefix":"","host":"localhost","port":"","scheme":"http"}